wmp/__init__.py
wmp/detect.py
wmp/utils.py
wmp/datasets/__init__.py
wmp/datasets/sample_image.jpg
wmp/datasets/sample_video.mp4
wmp/models/__init__.py
wmp/models/dlib_face_recognition_resnet_model_v1.dat
wmp/models/shape_predictor_68_face_landmarks.dat
wmp-0.2.0.dist-info/LICENSE
wmp-0.2.0.dist-info/METADATA
wmp-0.2.0.dist-info/WHEEL
wmp-0.2.0.dist-info/top_level.txt
wmp-0.2.0.dist-info/RECORD
