Metadata-Version: 2.1
Name: wmp
Version: 0.2.0
Summary: Module for face detection & recognition
Home-page: https://wmp-face.readthedocs.io
Author: Frederick Corpuz
Author-email: fcorpuz@wesleyan.edu
License: UNKNOWN
Platform: UNKNOWN
Classifier: Programming Language :: Python :: 3
Classifier: License :: OSI Approved :: MIT License
Classifier: Operating System :: OS Independent
Requires-Python: >=3.7
Requires-Dist: dlib (>=19.20.0)
Requires-Dist: numpy (>=1.19.0)
Requires-Dist: Pillow (>=7.2.0)
